[{
  "_id": {
    "$oid": "68123b79e731f1dca03f0245"
  },
  "property_id": "91f1fd2a-4362-4a09-a0b6-759617d59f29",
  "modification_date": "2025-01-10",
  "previous_price": 115583.42,
  "new_price": 343917.93,
  "reason": "market change",
  "oracle_id": 14
},
{
  "_id": {
    "$oid": "68123b79e731f1dca03f0249"
  },
  "property_id": "0ff40d35-a1e8-4f9c-9729-5ea2332ed1d0",
  "modification_date": "2025-01-08",
  "previous_price": 431133.61,
  "new_price": 193633.47,
  "reason": "renovation",
  "oracle_id": 18
},
{
  "_id": {
    "$oid": "68123b79e731f1dca03f023f"
  },
  "property_id": "d2f523a0-d556-44ac-8902-1c90ac13e305",
  "modification_date": "2023-12-07",
  "previous_price": 243369.76,
  "new_price": 323123.71,
  "reason": "owner request",
  "oracle_id": 8
},
{
  "_id": {
    "$oid": "68123b79e731f1dca03f0246"
  },
  "property_id": "b761b81b-07b7-4b49-b367-466e7fbe5eac",
  "modification_date": "2023-09-22",
  "previous_price": 347929.12,
  "new_price": 489674.55,
  "reason": "re-evaluation",
  "oracle_id": 15
},
{
  "_id": {
    "$oid": "68123b79e731f1dca03f0240"
  },
  "property_id": "4f9a3e35-8f8d-4705-b397-855580e14289",
  "modification_date": "2023-08-27",
  "previous_price": 412691.19,
  "new_price": 305163.33,
  "reason": "owner request",
  "oracle_id": 9
},
{
  "_id": {
    "$oid": "68123b79e731f1dca03f023b"
  },
  "property_id": "4be05ab6-bc4c-4816-a5ab-dcb666e32166",
  "modification_date": "2023-05-13",
  "previous_price": 138672.39,
  "new_price": 367153.13,
  "reason": "re-evaluation",
  "oracle_id": 4
}]